mytestlib/__init__.py
mytestlib/greet.py
mytestlib_higpen-1.0.15.dist-info/METADATA
mytestlib_higpen-1.0.15.dist-info/WHEEL
mytestlib_higpen-1.0.15.dist-info/top_level.txt
mytestlib_higpen-1.0.15.dist-info/RECORD
