Metadata-Version: 2.1
Name: mytestlib-higpen
Version: 1.0.15
Summary: My Test Library.
Author-email: higpen <higpen@higpen.higpen>
License: …
Project-URL: Homepage, https://…
